DataMemory.v
`timescale 1ns / 1ps

`define SIZE 1024

module DataMemory(ReadData , Address , WriteData , MemoryRead , MemoryWrite , Clock);
    input [63:0]      WriteData;
    input [63:0]      Address;
    input             Clock, MemoryRead, MemoryWrite;
    output reg [63:0] ReadData;

    reg [7:0]         memBank [`SIZE-1:0];


    // This task is used to write arbitrary data to the Data Memory by
    // the intialization block.
    task initset;
      input [63:0] addr;
      input [63:0] data;
      begin
     memBank[addr] =  data[63:56] ; // Big-endian for the win...
     memBank[addr+1] =  data[55:48];
     memBank[addr+2] =  data[47:40];
     memBank[addr+3] =  data[39:32];
     memBank[addr+4] =  data[31:24];
     memBank[addr+5] =  data[23:16];
     memBank[addr+6] =  data[15:8];
     memBank[addr+7] =  data[7:0];
     //$display("Writing Address:%h Data:%h", addr, data);
      end
    endtask


    initial
    begin
        // preseting some data in the data memory used by test #1
        // Address 0x0 gets 0x1
        initset( 64'h0,  64'h1);  //Counter variable
        initset( 64'h8,  64'ha);  //Part of mask
        initset( 64'h10, 64'h5);  //Other part of mask
        initset( 64'h18, 64'h0ffbea7deadbeeff); //big constant
        initset( 64'h20, 64'h0); //clearing space

        // Add any data you need for your tests here.

    end

    // This always block reads the data memory and places a double word
    // on the ReadData bus.
    always @(posedge Clock)
    begin
        if(MemoryRead)
        begin
            ReadData[63:56] <= #20 memBank[Address];
            ReadData[55:48] <= #20 memBank[Address+1];
            ReadData[47:40] <= #20 memBank[Address+2];
            ReadData[39:32] <= #20 memBank[Address+3];
            ReadData[31:24] <= #20 memBank[Address+4];
            ReadData[23:16] <= #20 memBank[Address+5];
            ReadData[15:8] <= #20 memBank[Address+6];
            ReadData[7:0] <= #20 memBank[Address+7];
            $display("Reading Address:%h Data:%h",Address, ReadData);
        end
        //$display("MemRead:%h", MemoryRead);

    end

    // This always block takes data from the WriteData bus and writes
    // it into the DataMemory.
    always @(posedge Clock)
    begin
        if(MemoryWrite)
        begin
            memBank[Address] <= #20 WriteData[63:56] ;
            memBank[Address+1] <= #20 WriteData[55:48];
            memBank[Address+2] <= #20 WriteData[47:40];
            memBank[Address+3] <= #20 WriteData[39:32];
            memBank[Address+4] <= #20 WriteData[31:24];
            memBank[Address+5] <= #20 WriteData[23:16];
            memBank[Address+6] <= #20 WriteData[15:8];
            memBank[Address+7] <= #20 WriteData[7:0];
            // Could be useful for debugging:
            //$display("Writing Address:%h Data:%h",Address, WriteData);
        end
        //$display("MemWrite:%h", MemoryWrite);
    end
endmodule

ALU.v
module ALU(BusA, BusB, ALUCtrl, Zero, BusW);
	input [63:0] BusA, BusB;
	input [3:0] ALUCtrl;
	output Zero;
	output reg [63:0] BusW;
	
always@(*)
begin
	if(ALUCtrl == 0)
	begin
	BusW <= #20 BusA & BusB;
	end
	if(ALUCtrl == 1)
	begin
	BusW <= #20 BusA | BusB;
	end
	if(ALUCtrl == 2)
	begin
	BusW <= #20 BusA + BusB;
	end
	if(ALUCtrl == 6)
	begin
	BusW <= #20 BusA - BusB;
	end
	if(ALUCtrl == 7)
	begin
	BusW <= #20 BusB;
	end
	//$display("BusA:%h", BusA);
end

assign #1 Zero = BusW ? 0 : 1;

endmodule

SignExtender.v
module SignExtender(BusImm, Imm25, Ctrl);
  output reg [63:0] BusImm; 
  input [25:0] Imm25; 
  input [1:0] Ctrl;

always@(*)
begin  
//$display("BusImm:%h", Imm25);
if(Ctrl == 2'b01) // D Instruction
	begin 
	BusImm = {{55{Imm25[20]}}, Imm25[20:12]}; 
	end
else if(Ctrl == 2'b00) // I Instruction
	begin 
	BusImm = {{52{Imm25[21]}}, Imm25[21:10]}; 
	end
else if(Ctrl == 2'b11) // CB Instruction
	begin 
	BusImm = {{45{Imm25[23]}}, Imm25[23:5]}; 
	end
else if(Ctrl == 2'b10) // B Instruction
	begin 
	BusImm = {{38{Imm25[25]}}, Imm25}; 
	end
end
endmodule

RegisterFile.v
module RegisterFile(BusA, BusB, BusW, RA, RB, RW, RegWr, Clk);
  input [63:0] BusW;
  input [4:0] RA, RB, RW;
  input RegWr;
  input Clk;
  output [63:0] BusA, BusB;
  reg [63:0] R [31:0];
  
  assign #2 BusA = R[RA];
  assign #2 BusB = R[RB];
  
  initial begin
    R[31] = 64'b0;
  end
  
  always @ (negedge Clk) 
  begin
    if(RegWr)
      R[RW] <= #3 BusW;
    
    R[31] = #3 64'b0;
      //$display("Register [%d]:%h", RB, BusB);
      //$display("Written:%h", RegWr);
  end
  
endmodule

SingleCycleControl.v
`define OPCODE_ANDREG 11'b?0001010???
`define OPCODE_ORRREG 11'b?0101010???
`define OPCODE_ADDREG 11'b?0?01011???
`define OPCODE_SUBREG 11'b?1?01011???

`define OPCODE_ADDIMM 11'b?0?10001???
`define OPCODE_SUBIMM 11'b?1?10001???

`define OPCODE_MOVZ   11'b110100101??

`define OPCODE_B      11'b?00101?????
`define OPCODE_CBZ    11'b?011010????

`define OPCODE_LDUR   11'b??111000010
`define OPCODE_STUR   11'b??111000000

module control(
    output reg reg2loc,
    output reg alusrc,
    output reg mem2reg,
    output reg regwrite,
    output reg memread,
    output reg memwrite,
    output reg branch,
    output reg uncond_branch,
    output reg [3:0] aluop,
    output reg [1:0] signop,
    input [10:0] opcode
);

always @(*)
begin
//$display("opcode:%b", opcode);
    casez (opcode)
        `OPCODE_ANDREG: 
        begin
            reg2loc <= 1'b0;
            uncond_branch <= 1'b0;
            branch <= 1'b0;
            memread <= 1'b0;
            mem2reg <= 1'b0;
            memwrite <= 1'b0;
            alusrc <= 1'b0;
            regwrite <= 1'b1;
            aluop <= 4'b0000;
            signop <= 2'bxx;
        end
        `OPCODE_ORRREG: 
        begin
            reg2loc <= 1'b0;
            uncond_branch <= 1'b0;
            branch <= 1'b0;
            memread <= 1'b0;
            mem2reg <= 1'b0;
            memwrite <= 1'b0;
            alusrc <= 1'b0;
            regwrite <= 1'b1;
            aluop <= 4'b0001;
            signop <= 2'bxx;
        end
        `OPCODE_ADDREG: 
        begin
            reg2loc <= 1'b0;
            uncond_branch <= 1'b0;
            branch <= 1'b0;
            memread <= 1'b0;
            mem2reg <= 1'b0;
            memwrite <= 1'b0;
            alusrc <= 1'b0;
            regwrite <= 1'b1;
            aluop <= 4'b0010;
            signop <= 2'bxx;
        end
        `OPCODE_SUBREG: 
        begin
            reg2loc <= 1'b0;
            uncond_branch <= 1'b0;
            branch <= 1'b0;
            memread <= 1'b0;
            mem2reg <= 1'b0;
            memwrite <= 1'b0;
            alusrc <= 1'b0;
            regwrite <= 1'b1;
            aluop <= 4'b0110;
            signop <= 2'bxx;
        end
        `OPCODE_ADDIMM: 
        begin
            reg2loc <= 1'bx;
            uncond_branch <= 1'b0;
            branch <= 1'b0;
            memread <= 1'b0;
            mem2reg <= 1'b0;
            memwrite <= 1'b0;
            alusrc <= 1'b1;
            regwrite <= 1'b1;
            aluop <= 4'b0010;
            signop <= 2'b00;
        end
        `OPCODE_SUBIMM: 
        begin
            reg2loc <= 1'bx;
            uncond_branch <= 1'b0;
            branch <= 1'b0;
            memread <= 1'b0;
            mem2reg <= 1'b0;
            memwrite <= 1'b0;
            alusrc <= 1'b1;
            regwrite <= 1'b1;
            aluop <= 4'b0110;
            signop <= 2'b00;
        end
        `OPCODE_MOVZ: 
        begin
            reg2loc <= 1'bx;
            uncond_branch <= 1'b0;
            branch <= 1'b0;
            memread <= 1'b0;
            mem2reg <= 1'b0;
            memwrite <= 1'b0;
            alusrc <= 1'b1;
            regwrite <= 1'b1;
            aluop <= 4'b0111;
            signop <= 2'b01;
        end
        `OPCODE_B: 
        begin
            reg2loc <= 1'bx;
            uncond_branch <= 1'b1;
            branch <= 1'bx;
            memread <= 1'b0;
            mem2reg <= 1'bx;
            memwrite <= 1'b0;
            alusrc <= 1'bx;
            regwrite <= 1'b0;
            aluop <= 4'bxxxx;
            signop <= 2'b10;
        end
        `OPCODE_CBZ: 
        begin
            reg2loc <= 1'b1;
            uncond_branch <= 1'b0;
            branch <= 1'b1;
            memread <= 1'b0;
            mem2reg <= 1'bx;
            memwrite <= 1'b0;
            alusrc <= 1'b0;
            regwrite <= 1'b0;
            aluop <= 4'b0111;
            signop <= 2'b11;
        end
        `OPCODE_LDUR: 
        begin
            reg2loc <= 1'bx;
            uncond_branch <= 1'b0;
            branch <= 1'b0;
            memread <= 1'b1;
            mem2reg <= 1'b1;
            memwrite <= 1'b0;
            alusrc <= 1'b1;
            regwrite <= 1'b1;
            aluop <= 4'b0010;
            signop <= 2'b01;
        end
        `OPCODE_STUR: 
        begin
            reg2loc <= 1'b1;
            uncond_branch <= 1'b0;
            branch <= 1'b0;
            memread <= 1'b0;
            mem2reg <= 1'bx;
            memwrite <= 1'b1;
            alusrc <= 1'b1;
            regwrite <= 1'b0;
            aluop <= 4'b0010;
            signop <= 2'b01;
        end
        default:
        begin
            reg2loc       <= 1'bx;
            alusrc        <= 1'bx;
            mem2reg       <= 1'bx;
            regwrite      <= 1'b0;
            memread       <= 1'b0;
            memwrite      <= 1'b0;
            branch        <= 1'b0;
            uncond_branch <= 1'b0;
            aluop         <= 4'bxxxx;
            signop        <= 2'bxx;
        end
    endcase
end

endmodule

NextPCLogic.v
module NextPCLogic(NextPC, CurrentPC, SignExtImm64, Branch, ALUZero, Uncondbranch); 
    input [63:0] CurrentPC, SignExtImm64; 
    input Branch, ALUZero, Uncondbranch; 
    output reg [63:0] NextPC; 

always @ (*)
begin
    if (Uncondbranch) // B Instructions
	NextPC = CurrentPC + (SignExtImm64 << 2);
    else if (ALUZero && Branch) // CB Instructions
	NextPC = CurrentPC + (SignExtImm64 << 2);
    else // Default case
	NextPC = CurrentPC + 4;
end	
	
endmodule

InstructionMemory.v
`timescale 1ns / 1ps
/*
 * Module: InstructionMemory
 *
 * Implements read-only instruction memory
 * 
 */
module InstructionMemory(Data, Address);
   parameter T_rd = 20;
   parameter MemSize = 40;
   
   output [31:0] Data;
   input [63:0]  Address;
   reg [31:0] 	 Data;
   
   /*
    * ECEN 350 Processor Test Functions
    * Texas A&M University
    */
   
   always @ (Address) begin
      #4;
      case(Address)

	/* Test Program 1:
	 * Program loads constants from the data memory. Uses these constants to test
	 * the following instructions: LDUR, ORR, AND, CBZ, ADD, SUB, STUR and B.
	 * 
	 * Assembly code for test:
	 * 
	 * 0: LDUR X9, [XZR, 0x0]    //Load 1 into x9
	 * 4: LDUR X10, [XZR, 0x8]   //Load a into x10
	 * 8: LDUR X11, [XZR, 0x10]  //Load 5 into x11
	 * C: LDUR X12, [XZR, 0x18]  //Load big constant into x12
	 * 10: LDUR X13, [XZR, 0x20]  //load a 0 into X13
	 * 
	 * 14: ORR X10, X10, X11  //Create mask of 0xf
	 * 18: AND X12, X12, X10  //Mask off low order bits of big constant
	 * 
	 * loop:
	 * 1C: CBZ X12, end  //while X12 is not 0
	 * 20: ADD X13, X13, X9  //Increment counter in X13
	 * 24: SUB X12, X12, X9  //Decrement remainder of big constant in X12
	 * 28: B loop  //Repeat till X12 is 0
	 * 2C: STUR X13, [XZR, 0x20]  //store back the counter value into the memory location 0x20
	 */
	

	63'h000: Data = 32'hF84003E9;
	63'h004: Data = 32'hF84083EA;
	63'h008: Data = 32'hF84103EB;
	63'h00c: Data = 32'hF84183EC;
	63'h010: Data = 32'hF84203ED;
	63'h014: Data = 32'hAA0B014A;
	63'h018: Data = 32'h8A0A018C;
	63'h01c: Data = 32'hB400008C;
	63'h020: Data = 32'h8B0901AD;
	63'h024: Data = 32'hCB09018C;
	63'h028: Data = 32'h17FFFFFD;
	63'h02c: Data = 32'hF80203ED;
	63'h030: Data = 32'hF84203ED;  //One last load to place stored value on memdbus for test checking.

	/* Add code for your tests here */
	
	/*
	ADD X1, X31, #1
	ADD X2, X31, #10
	ADD X3,X1,X2
	STUR X4, [XZR, 0x34]
	LDUR X9, [XZR, 0x34]
	*/
	
	63'h040: Data = 32'h910007E1;
	63'h044: Data = 32'h91002BE2;
	63'h048: Data = 32'h8B020023;
	63'h04c: Data = 32'hF80403E3;
	63'h050: Data = 32'hF84403E9;

	default: Data = 32'hXXXXXXXX;
      endcase
   end
   
   	always @(Address)
    begin
            // Could be useful for debugging:
            //$display("Writing Address:%h Data:%h",Address, Data);
    end
   
endmodule

SingleCycleProc.v
module singlecycle(
    input resetl,
    input [63:0] startpc,
    output reg [63:0] currentpc,
    output [63:0] dmemout,
    input CLK
);

    // Next PC connections
    wire [63:0] nextpc;       // The next PC, to be updated on clock cycle

    // Instruction Memory connections
    wire [31:0] instruction;  // The current instruction

    // Parts of instruction
    wire [4:0] rd;            // The destination register
    wire [4:0] rm;            // Operand 1
    wire [4:0] rn;            // Operand 2
    wire [10:0] opcode;

    // Control wires
    wire reg2loc;
    wire alusrc;
    wire mem2reg;
    wire regwrite;
    wire memread;
    wire memwrite;
    wire branch;
    wire uncond_branch;
    wire [3:0] aluctrl;
    wire [1:0] signop;

    // Register file connections
    wire [63:0] regoutA;     // Output A
    wire [63:0] regoutB;     // Output B

    // ALU connections
    wire [63:0] aluout;
    wire zero;
    
    //Data Memory Wires
    wire [63:0] dmemout;
    
    // Sign Extender connections
    wire [63:0] extimm;
    wire [25:0] Imm25;

    // PC update logic
    always @(negedge CLK)
    begin
        if (resetl)
            currentpc <= nextpc;
        else
            currentpc <= startpc;
    end

    // Parts of instruction
    assign rd = instruction[4:0];
    assign rm = instruction[9:5];
    assign rn = reg2loc ? instruction[4:0] : instruction[20:16];
    assign opcode = instruction[31:21];
    assign Imm25 = instruction[25:0];
    
    // MUX outputs
    wire [63:0] alu_mux;
    wire [63:0] write_mux;
    
    InstructionMemory imem(
        .Data(instruction),
        .Address(currentpc)
    );
    
    NextPCLogic NextPC(
        .NextPC(nextpc), 
        .CurrentPC(currentpc), 
        .SignExtImm64(extimm), 
        .Branch(branch), 
        .ALUZero(zero), 
        .Uncondbranch(uncond_branch)
    );

    control control(
        .reg2loc(reg2loc),
        .alusrc(alusrc),
        .mem2reg(mem2reg),
        .regwrite(regwrite),
        .memread(memread),
        .memwrite(memwrite),
        .branch(branch),
        .uncond_branch(uncond_branch),
        .aluop(aluctrl),
        .signop(signop),
        .opcode(opcode)
    );
    
    RegisterFile RegFile(
        .BusA(regoutA),
        .BusB(regoutB), 
        .BusW(write_mux),
        .RA(rm), 
        .RB(rn), 
        .RW(rd), 
        .RegWr(regwrite), 
        .Clk(CLK)
    );

    SignExtender SignExt(
        .BusImm(extimm), 
        .Imm25(Imm25), 
        .Ctrl(signop)
    );
    
    assign alu_mux = alusrc ? extimm : regoutB;

    ALU ALU(
        .BusW(aluout), 
        .Zero(zero),
        .BusA(regoutA), 
        .BusB(alu_mux),
        .ALUCtrl(aluctrl)
    );

    DataMemory datamem(
        .ReadData(dmemout),
        .Address(aluout), 
        .WriteData(regoutB), 
        .MemoryRead(memread),
        .MemoryWrite(memwrite), 
        .Clock(CLK)
    );

    assign write_mux = mem2reg ? dmemout : aluout;

endmodule

SingleCycleProcTest.v
`timescale 1ns / 1ps

`define STRLEN 32
`define HalfClockPeriod 60
`define ClockPeriod `HalfClockPeriod * 2

module SingleCycleProcTest_v;

    initial
    begin
        $dumpfile("singlecycle.vcd");
        $dumpvars;
    end

    // These tasks are used to check if a given test has passed and
    // confirm that all tests passed.
    task passTest;
        input [63:0] actualOut, expectedOut;
        input [`STRLEN*8:0] testType;
        inout [7:0] 	  passed;

        if(actualOut == expectedOut) begin $display ("%s passed", testType); passed = passed + 1; end
        else $display ("%s failed: 0x%x should be 0x%x", testType, actualOut, expectedOut);
    endtask

    task allPassed;
        input [7:0] passed;
        input [7:0] numTests;

        if(passed == numTests) $display ("All tests passed");
        else $display("Some tests failed: %d of %d passed", passed, numTests);
    endtask

    // Inputs
    reg        CLK;
    reg        Reset_L;
    reg [63:0] startPC;
    reg [7:0]  passed;
    reg [15:0] watchdog;

    // Outputs
    wire [63:0] dMemOut;
    wire [63:0] currentPC;

    // Instantiate the Unit Under Test (UUT)
    singlecycle uut (
        .CLK(CLK),
        .resetl(Reset_L),
        .startpc(startPC),
        .currentpc(currentPC),
        .dmemout(dMemOut)
    );

    initial begin
        // Initialize Inputs
        Reset_L = 1;
        startPC = 0;
        passed = 0;

        // Initialize Watchdog timer
        watchdog = 0;

        // Wait for global reset
        #(1 * `ClockPeriod);

        // Program 1
        #1
        Reset_L = 0; startPC = 0;
        #(1 * `ClockPeriod);
        Reset_L = 1;

        // ***********************************************************
        // This while loop will continue cycling the processor until the
        // PC reaches the final instruction in the first test.  If the
        // program forms an infinite loop, never reaching the end, the
        // watchdog timer will kick in and kill simulation after 64K
        // cycles.
        // ***********************************************************

        while (currentPC < 64'h34)
        begin
           #(1 * `ClockPeriod);
           $display("CurrentPC:%h",currentPC);
        end
        #(1 * `ClockPeriod);	// One more cycle to load the pass code from the DataMemory.
        passTest(dMemOut, 64'hF, "Results of Program 1", passed);

        // ***********************************************************
        // Add your new tests here
        // ***********************************************************

        #1
        Reset_L = 0; startPC = 63'h040;
        #(1 * `ClockPeriod);
        Reset_L = 1;
		
        while (currentPC < 64'h54)
        begin
           #(1 * `ClockPeriod);
           $display("CurrentPC:%h",currentPC);
        end
        #(1 * `ClockPeriod);	// One more cycle to load the pass code from the DataMemory.
        passTest(dMemOut, 64'hB, "Results of Program 2", passed);

        // Done
        allPassed(passed, 2);   // Be sure to change the one to match
                                // the number of tests you add.
        $finish;
    end

    initial begin
        CLK = 0;
    end

    // The following is correct if clock starts at LOW level at StartTime //
    always begin
        #`HalfClockPeriod CLK = ~CLK;
        #`HalfClockPeriod CLK = ~CLK;
        watchdog = watchdog +1;
    end

    // Kill the simulation if the watchdog hits 64K cycles
    always @*
        if (watchdog == 16'hFF)
        begin
            $display("Watchdog Timer Expired.");
            $finish;
        end


endmodule

singlecycle.vcd
$date
	Thu Dec  9 16:04:50 2021
$end
$version
	Icarus Verilog
$end
$timescale
	1ps
$end
$scope module SingleCycleProcTest_v $end
$var wire 64 ! dMemOut [63:0] $end
$var wire 64 " currentPC [63:0] $end
$var reg 1 # CLK $end
$var reg 1 $ Reset_L $end
$var reg 8 % passed [7:0] $end
$var reg 64 & startPC [63:0] $end
$var reg 16 ' watchdog [15:0] $end
$scope module uut $end
$var wire 1 # CLK $end
$var wire 1 $ resetl $end
$var wire 64 ( startpc [63:0] $end
$var wire 1 ) zero $end
$var wire 64 * write_mux [63:0] $end
$var wire 1 + uncond_branch $end
$var wire 2 , signop [1:0] $end
$var wire 5 - rn [4:0] $end
$var wire 5 . rm [4:0] $end
$var wire 1 / regwrite $end
$var wire 64 0 regoutB [63:0] $end
$var wire 64 1 regoutA [63:0] $end
$var wire 1 2 reg2loc $end
$var wire 5 3 rd [4:0] $end
$var wire 11 4 opcode [10:0] $end
$var wire 64 5 nextpc [63:0] $end
$var wire 1 6 memwrite $end
$var wire 1 7 memread $end
$var wire 1 8 mem2reg $end
$var wire 32 9 instruction [31:0] $end
$var wire 64 : extimm [63:0] $end
$var wire 64 ; dmemout [63:0] $end
$var wire 1 < branch $end
$var wire 1 = alusrc $end
$var wire 64 > aluout [63:0] $end
$var wire 4 ? aluctrl [3:0] $end
$var wire 64 @ alu_mux [63:0] $end
$var wire 26 A Imm25 [25:0] $end
$var reg 64 B currentpc [63:0] $end
$scope module ALU $end
$var wire 64 C BusB [63:0] $end
$var wire 1 ) Zero $end
$var wire 64 D BusA [63:0] $end
$var wire 4 E ALUCtrl [3:0] $end
$var reg 64 F BusW [63:0] $end
$upscope $end
$scope module NextPC $end
$var wire 1 ) ALUZero $end
$var wire 64 G CurrentPC [63:0] $end
$var wire 1 + Uncondbranch $end
$var wire 64 H SignExtImm64 [63:0] $end
$var wire 1 < Branch $end
$var reg 64 I NextPC [63:0] $end
$upscope $end
$scope module RegFile $end
$var wire 64 J BusA [63:0] $end
$var wire 64 K BusB [63:0] $end
$var wire 64 L BusW [63:0] $end
$var wire 1 # Clk $end
$var wire 5 M RA [4:0] $end
$var wire 5 N RB [4:0] $end
$var wire 5 O RW [4:0] $end
$var wire 1 / RegWr $end
$upscope $end
$scope module SignExt $end
$var wire 26 P Imm25 [25:0] $end
$var wire 2 Q Ctrl [1:0] $end
$var reg 64 R BusImm [63:0] $end
$upscope $end
$scope module control $end
$var wire 11 S opcode [10:0] $end
$var reg 4 T aluop [3:0] $end
$var reg 1 = alusrc $end
$var reg 1 < branch $end
$var reg 1 8 mem2reg $end
$var reg 1 7 memread $end
$var reg 1 6 memwrite $end
$var reg 1 2 reg2loc $end
$var reg 1 / regwrite $end
$var reg 2 U signop [1:0] $end
$var reg 1 + uncond_branch $end
$upscope $end
$scope module datamem $end
$var wire 64 V Address [63:0] $end
$var wire 1 # Clock $end
$var wire 1 7 MemoryRead $end
$var wire 1 6 MemoryWrite $end
$var wire 64 W WriteData [63:0] $end
$var reg 64 X ReadData [63:0] $end
$scope task initset $end
$var reg 64 Y addr [63:0] $end
$var reg 64 Z data [63:0] $end
$upscope $end
$upscope $end
$scope module imem $end
$var wire 64 [ Address [63:0] $end
$var reg 32 \ Data [31:0] $end
$upscope $end
$upscope $end
$scope task allPassed $end
$var reg 8 ] numTests [7:0] $end
$var reg 8 ^ passed [7:0] $end
$upscope $end
$scope task passTest $end
$var reg 64 _ actualOut [63:0] $end
$var reg 64 ` expectedOut [63:0] $end
$var reg 8 a passed [7:0] $end
$var reg 257 b testType [256:0] $end
$upscope $end
$upscope $end
$enddefinitions $end
#0
$dumpvars
bx b
bx a
bx `
bx _
bx ^
bx ]
bx \
bx [
b0 Z
b100000 Y
bx X
bx W
bx V
bx U
bx T
bx S
bx R
bx Q
bx P
bx O
bx N
bx M
bx L
bx K
bx J
bx I
bx H
bx G
bx F
bx E
bx D
bx C
bx B
bx A
bx @
bx ?
bx >
x=
x<
bx ;
bx :
bx 9
x8
x7
x6
bx 5
bx 4
bx 3
x2
bx 1
bx 0
x/
bx .
bx -
bx ,
x+
bx *
x)
b0 (
b0 '
b0 &
b0 %
1$
0#
bx "
bx !
$end
#60000
1#
#120000
b1 '
0#
#121000
0$
#180000
1#
#240000
b100 5
b100 I
b0 "
b0 B
b0 G
b0 [
b10 '
0#
#241000
1$
#244000
b0 @
b0 C
b0 :
b0 H
b0 R
b1 ,
b1 Q
b1 U
b10 ?
b10 E
b10 T
1/
1=
06
18
17
0<
0+
b0x00x -
b0x00x N
b10000000000001111101001 A
b10000000000001111101001 P
b11111000010 4
b11111000010 S
b11111 .
b11111 M
b1001 3
b1001 O
b11111000010000000000001111101001 9
b11111000010000000000001111101001 \
#246000
b0 1
b0 D
b0 J
#266000
b0 >
b0 F
b0 V
#267000
1)
#300000
1#
#320000
b1 *
b1 L
b1 !
b1 ;
b1 X
#360000
b1000 5
b1000 I
b100 "
b100 B
b100 G
b100 [
b11 '
0#
#364000
b1000 @
b1000 C
b1000 :
b1000 H
b1000 R
b0x0x0 -
b0x0x0 N
b10000001000001111101010 A
b10000001000001111101010 P
b1010 3
b1010 O
b11111000010000001000001111101010 9
b11111000010000001000001111101010 \
#384000
b1000 >
b1000 F
b1000 V
#385000
0)
#420000
1#
#440000
b1010 *
b1010 L
b1010 !
b1010 ;
b1010 X
#480000
b1100 5
b1100 I
b1000 "
b1000 B
b1000 G
b1000 [
b100 '
0#
#484000
b10000 @
b10000 C
b10000 :
b10000 H
b10000 R
b0x0x1 -
b0x0x1 N
b10000010000001111101011 A
b10000010000001111101011 P
b1011 3
b1011 O
b11111000010000010000001111101011 9
b11111000010000010000001111101011 \
#504000
b10000 >
b10000 F
b10000 V
#540000
1#
#560000
b101 *
b101 L
b101 !
b101 ;
b101 X
#600000
b10000 5
b10000 I
b1100 "
b1100 B
b1100 G
b1100 [
b101 '
0#
#604000
b11000 @
b11000 C
b11000 :
b11000 H
b11000 R
b0xx0x -
b0xx0x N
b10000011000001111101100 A
b10000011000001111101100 P
b1100 3
b1100 O
b11111000010000011000001111101100 9
b11111000010000011000001111101100 \
#624000
b11000 >
b11000 F
b11000 V
#660000
1#
#680000
b111111111011111010100111110111101010110110111110111011111111 *
b111111111011111010100111110111101010110110111110111011111111 L
b111111111011111010100111110111101010110110111110111011111111 !
b111111111011111010100111110111101010110110111110111011111111 ;
b111111111011111010100111110111101010110110111110111011111111 X
#720000
b10100 5
b10100 I
b10000 "
b10000 B
b10000 G
b10000 [
b110 '
0#
#724000
b100000 @
b100000 C
b100000 :
b100000 H
b100000 R
b0xxxx -
b0xxxx N
b10000100000001111101101 A
b10000100000001111101101 P
b1101 3
b1101 O
b11111000010000100000001111101101 9
b11111000010000100000001111101101 \
#744000
b100000 >
b100000 F
b100000 V
#780000
1#
#800000
b0 *
b0 L
b0 !
b0 ;
b0 X
#840000
b11000 5
b11000 I
b10100 "
b10100 B
b10100 G
b10100 [
b111 '
0#
#844000
b100000 *
b100000 L
bx ,
bx Q
bx U
b1 ?
b1 E
b1 T
0=
08
07
02
bx @
bx C
b10110000 :
b10110000 H
b10110000 R
b1011 -
b1011 N
b10000010110000000101001010 A
b10000010110000000101001010 P
b10101010000 4
b10101010000 S
b1010 .
b1010 M
b1010 3
b1010 O
b10101010000010110000000101001010 9
b10101010000010110000000101001010 \
#846000
b101 @
b101 C
b101 0
b101 K
b101 W
b1010 1
b1010 D
b1010 J
#864000
bx *
bx L
bx >
bx F
bx V
#865000
x)
#866000
b1111 *
b1111 L
b1111 >
b1111 F
b1111 V
#867000
0)
#900000
1#
#960000
b11100 5
b11100 I
b11000 "
b11000 B
b11000 G
b11000 [
b1000 '
0#
#964000
b0 ?
b0 E
b0 T
b1010 -
b1010 N
b10000010100000000110001100 A
b10000010100000000110001100 P
b10001010000 4
b10001010000 S
b1100 .
b1100 M
b1100 3
b1100 O
b10001010000010100000000110001100 9
b10001010000010100000000110001100 \
#966000
b1111 @
b1111 C
b1111 0
b1111 K
b1111 W
b111111111011111010100111110111101010110110111110111011111111 1
b111111111011111010100111110111101010110110111110111011111111 D
b111111111011111010100111110111101010110110111110111011111111 J
#984000
b0 *
b0 L
b0 >
b0 F
b0 V
#985000
1)
#986000
b1111 *
b1111 L
b1111 >
b1111 F
b1111 V
#987000
0)
#1020000
1#
#1080000
b100000 5
b100000 I
b11100 "
b11100 B
b11100 G
b11100 [
b1001 '
0#
#1084000
b100 :
b100 H
b100 R
b0xxxx *
b0xxxx L
b11 ,
b11 Q
b11 U
b111 ?
b111 E
b111 T
0/
x8
1<
12
b1100 -
b1100 N
b10001100 A
b10001100 P
b10110100000 4
b10110100000 S
b100 .
b100 M
b10110100000000000000000010001100 9
b10110100000000000000000010001100 \
#1086000
bx 1
bx D
bx J
#1140000
1#
#1200000
b100100 5
b100100 I
b100000 "
b100000 B
b100000 G
b100000 [
b1010 '
0#
#1204000
b1111 *
b1111 L
bx ,
bx Q
bx U
b10 ?
b10 E
b10 T
1/
08
0<
02
b100100000001101 :
b100100000001101 H
b100100000001101 R
b1001 -
b1001 N
b11000010010000000110101101 A
b11000010010000000110101101 P
b10001011000 4
b10001011000 S
b1101 .
b1101 M
b1101 3
b1101 O
b10001011000010010000000110101101 9
b10001011000010010000000110101101 \
#1206000
b1 @
b1 C
b1 0
b1 K
b1 W
b0 1
b0 D
b0 J
#1224000
bx *
bx L
bx >
bx F
bx V
#1225000
x)
#1226000
b1 *
b1 L
b1 >
b1 F
b1 V
#1227000
0)
#1260000
1#
#1320000
b101000 5
b101000 I
b100100 "
b100100 B
b100100 G
b100100 [
b1011 '
0#
#1324000
b110 ?
b110 E
b110 T
b11000010010000000110001100 A
b11000010010000000110001100 P
b11001011000 4
b11001011000 S
b1100 .
b1100 M
b1100 3
b1100 O
b11001011000010010000000110001100 9
b11001011000010010000000110001100 \
#1326000
b1111 1
b1111 D
b1111 J
#1344000
b1111111111111111111111111111111111111111111111111111111111111111 *
b1111111111111111111111111111111111111111111111111111111111111111 L
b1111111111111111111111111111111111111111111111111111111111111111 >
b1111111111111111111111111111111111111111111111111111111111111111 F
b1111111111111111111111111111111111111111111111111111111111111111 V
#1346000
b1110 *
b1110 L
b1110 >
b1110 F
b1110 V
#1380000
1#
#1440000
b101100 5
b101100 I
b101000 "
b101000 B
b101000 G
b101000 [
b1100 '
0#
#1444000
b1111111111111111111111111111111111111111111111111111111111111101 :
b1111111111111111111111111111111111111111111111111111111111111101 H
b1111111111111111111111111111111111111111111111111111111111111101 R
bx01 @
bx01 C
b0xxx0 *
b0xxx0 L
b11100 5
b11100 I
b10 ,
b10 Q
b10 U
bx ?
bx E
bx T
0/
x=
x8
x<
1+
x2
b111x1 -
b111x1 N
b11111111111111111111111101 A
b11111111111111111111111101 P
b10111111 4
b10111111 S
b11111 .
b11111 M
b11101 3
b11101 O
b10111111111111111111111111101 9
b10111111111111111111111111101 \
#1446000
bx @
bx C
bx 0
bx K
bx W
b0 1
b0 D
b0 J
#1500000
1#
#1560000
b10000 5
b10000 I
b11100 "
b11100 B
b11100 G
b11100 [
b1101 '
0#
#1564000
b11 ,
b11 Q
b11 U
b111 ?
b111 E
b111 T
0=
1<
0+
12
b100000 5
b100000 I
b100 :
b100 H
b100 R
b1100 -
b1100 N
b10001100 A
b10001100 P
b10110100000 4
b10110100000 S
b100 .
b100 M
b1100 3
b1100 O
b10110100000000000000000010001100 9
b10110100000000000000000010001100 \
#1566000
b1110 @
b1110 C
b1110 0
b1110 K
b1110 W
bx 1
bx D
bx J
#1584000
bx *
bx L
bx >
bx F
bx V
#1585000
x)
#1586000
b0xxx0 *
b0xxx0 L
b1110 >
b1110 F
b1110 V
#1587000
0)
#1620000
1#
#1680000
b100100 5
b100100 I
b100000 "
b100000 B
b100000 G
b100000 [
b1110 '
0#
